{
  "id": "3310806",
  "name": "page1",
  "font_family": "iconfont",
  "css_prefix_text": "icon-",
  "description": "",
  "glyphs": [
    {
      "icon_id": "8820137",
      "name": "屏蔽",
      "font_class": "pingbi",
      "unicode": "e6c5",
      "unicode_decimal": 59077
    },
    {
      "icon_id": "577382",
      "name": "喜欢",
      "font_class": "xihuan",
      "unicode": "e761",
      "unicode_decimal": 59233
    },
    {
      "icon_id": "1505555",
      "name": "旅游",
      "font_class": "lvyou",
      "unicode": "e601",
      "unicode_decimal": 58881
    },
    {
      "icon_id": "3856466",
      "name": "旅游鞋",
      "font_class": "lvyouxie",
      "unicode": "e61c",
      "unicode_decimal": 58908
    },
    {
      "icon_id": "3900141",
      "name": "旅游主题_火车",
      "font_class": "tubiaozhizuomoban_huoche",
      "unicode": "e608",
      "unicode_decimal": 58888
    },
    {
      "icon_id": "3900149",
      "name": "旅游主题_美食",
      "font_class": "tubiaozhizuomoban_meishi",
      "unicode": "e609",
      "unicode_decimal": 58889
    },
    {
      "icon_id": "5318209",
      "name": "酒店",
      "font_class": "jiudian",
      "unicode": "e687",
      "unicode_decimal": 59015
    },
    {
      "icon_id": "9974429",
      "name": "省略号",
      "font_class": "shenglvehao",
      "unicode": "e708",
      "unicode_decimal": 59144
    },
    {
      "icon_id": "13078329",
      "name": "游艇",
      "font_class": "youting",
      "unicode": "e645",
      "unicode_decimal": 58949
    },
    {
      "icon_id": "667792",
      "name": "评论",
      "font_class": "pinglun1",
      "unicode": "e6ad",
      "unicode_decimal": 59053
    },
    {
      "icon_id": "6337455",
      "name": "点赞",
      "font_class": "dianzan",
      "unicode": "ec7f",
      "unicode_decimal": 60543
    },
    {
      "icon_id": "11372666",
      "name": "分享",
      "font_class": "fenxiang",
      "unicode": "e8b0",
      "unicode_decimal": 59568
    },
    {
      "icon_id": "11372728",
      "name": "眼睛",
      "font_class": "yanjing",
      "unicode": "e8bf",
      "unicode_decimal": 59583
    },
    {
      "icon_id": "17546280",
      "name": "评论",
      "font_class": "pinglun",
      "unicode": "e607",
      "unicode_decimal": 58887
    },
    {
      "icon_id": "145491",
      "name": "箭头",
      "font_class": "jiantou",
      "unicode": "e662",
      "unicode_decimal": 58978
    },
    {
      "icon_id": "3791134",
      "name": "钱钱-01",
      "font_class": "qianqian-",
      "unicode": "e606",
      "unicode_decimal": 58886
    },
    {
      "icon_id": "963809",
      "name": "个人中心",
      "font_class": "gerenzhongxin",
      "unicode": "e61e",
      "unicode_decimal": 58910
    },
    {
      "icon_id": "10392614",
      "name": "登录",
      "font_class": "denglu",
      "unicode": "e605",
      "unicode_decimal": 58885
    },
    {
      "icon_id": "1360",
      "name": "新浪微博",
      "font_class": "xinlangweibo",
      "unicode": "e602",
      "unicode_decimal": 58882
    },
    {
      "icon_id": "5027",
      "name": "手机",
      "font_class": "shouji",
      "unicode": "e603",
      "unicode_decimal": 58883
    },
    {
      "icon_id": "77156",
      "name": "微信",
      "font_class": "weixin",
      "unicode": "e604",
      "unicode_decimal": 58884
    },
    {
      "icon_id": "5387648",
      "name": "电话",
      "font_class": "dianhua",
      "unicode": "eb23",
      "unicode_decimal": 60195
    },
    {
      "icon_id": "124495",
      "name": "警告",
      "font_class": "jinggao",
      "unicode": "e600",
      "unicode_decimal": 58880
    },
    {
      "icon_id": "446577",
      "name": "价格保证",
      "font_class": "jiagebaozheng",
      "unicode": "e60f",
      "unicode_decimal": 58895
    },
    {
      "icon_id": "630128",
      "name": "照相机",
      "font_class": "zhaoxiangji",
      "unicode": "e663",
      "unicode_decimal": 58979
    },
    {
      "icon_id": "1486844",
      "name": "退订",
      "font_class": "tuiding",
      "unicode": "e631",
      "unicode_decimal": 58929
    },
    {
      "icon_id": "2076273",
      "name": "问答",
      "font_class": "wenda",
      "unicode": "e893",
      "unicode_decimal": 59539
    },
    {
      "icon_id": "3930501",
      "name": "点评",
      "font_class": "dianping",
      "unicode": "e61b",
      "unicode_decimal": 58907
    },
    {
      "icon_id": "5387705",
      "name": "服务",
      "font_class": "fuwu",
      "unicode": "eb36",
      "unicode_decimal": 60214
    },
    {
      "icon_id": "5482900",
      "name": "兔子",
      "font_class": "tuzi",
      "unicode": "e679",
      "unicode_decimal": 59001
    },
    {
      "icon_id": "6129088",
      "name": "52上滑",
      "font_class": "shanghua",
      "unicode": "e76e",
      "unicode_decimal": 59246
    },
    {
      "icon_id": "10069734",
      "name": "公告",
      "font_class": "gonggao",
      "unicode": "e672",
      "unicode_decimal": 58994
    },
    {
      "icon_id": "17164665",
      "name": "救援中心",
      "font_class": "jiuyuanzhongxin",
      "unicode": "e673",
      "unicode_decimal": 58995
    }
  ]
}
